tool_use/__init__.py
tool_use/cli.py
tool_use/config_manager.py
tool_use/core.py
tool_use/scripts/_script_dependencies.py
tool_use/scripts/activity_tracker.py
tool_use/scripts/ai_cli.py
tool_use/scripts/cal.py
tool_use/scripts/convert.py
tool_use/scripts/marketing_agency.py
tool_use/scripts/obsidian_plugin.py
tool_use/scripts/posture.py
tool_use/scripts/prioritize.py
tool_use/scripts/promptathon.py
tool_use/scripts/transcribe.py
tool_use/tooluse/cli.py
tool_use/tooluse/contact.py
tool_use/tooluse/rss.py
tool_use/utils/ai_service.py
tool_use/utils/config_wizard.py
tool_use/utils/core.py
tool_use/utils/shallowgram.py
tool_use_ai-1.1.11.dist-info/METADATA
tool_use_ai-1.1.11.dist-info/WHEEL
tool_use_ai-1.1.11.dist-info/entry_points.txt
tool_use_ai-1.1.11.dist-info/RECORD
