Metadata-Version: 2.1
Name: tool-use-ai
Version: 1.1.11
Summary: Tools to simplify life with AI
License: MIT
Author: Ty Fiero
Author-email: tyfierodev@gmail.com
Requires-Python: >=3.11,<4.0
Classifier: License :: OSI Approved :: MIT License
Classifier: Operating System :: OS Independent
Classifier: Programming Language :: Python :: 3
Classifier: Programming Language :: Python :: 3.11
Classifier: Programming Language :: Python :: 3.12
Classifier: Programming Language :: Python :: 3.13
Requires-Dist: anthropic (>=0.21.0,<0.22.0)
Requires-Dist: feedparser (>=6.0.11,<7.0.0)
Requires-Dist: google-api-python-client (>=2.149.0,<3.0.0)
Requires-Dist: google-auth-oauthlib (>=1.0.0,<2.0.0)
Requires-Dist: groq (==0.11.0)
Requires-Dist: inquirer (>=3.4.0,<4.0.0)
Requires-Dist: ollama (>=0.1.6,<0.2.0)
Requires-Dist: openai (>=1.54.4,<2.0.0)
Requires-Dist: prompt-toolkit (>=3.0.48,<4.0.0)
Requires-Dist: pydantic (>=2.9.2,<3.0.0)
Requires-Dist: pynput (>=1.7.7,<2.0.0)
Requires-Dist: pytz (>=2024.2,<2025.0)
Requires-Dist: rich (>=13.9.2,<14.0.0)
Requires-Dist: sounddevice (>=0.5.1,<0.6.0)
Requires-Dist: soundfile (>=0.12.1,<0.13.0)
Requires-Dist: tomli (>=2.0.2,<3.0.0)
Requires-Dist: tomli-w (>=1.1.0,<2.0.0)
Requires-Dist: tzlocal (>=5.2,<6.0)
Project-URL: Bug Tracker, https://github.com/ToolUse/tool-use-ai/issues
Project-URL: Documentation, https://github.com/ToolUse/tool-use-ai#readme
Project-URL: Homepage, https://github.com/ToolUse/tool-use-ai
